vnet/api/__init__.py
vnet/api/mq.py
vnet/api/response_vo.py
vnet/api/router.py
vnet/api/score.py
vnet/api/validation.py
vnet/api/vnet_controller.py
vnet/judge_host/network_simulator.py
vnet/judge_host/server.py
vnet/judge_host/socket_manager.py
vnet/layers/__init__.py
vnet/layers/application/__init__.py
vnet/layers/application/http.py
vnet/layers/application/http_header.py
vnet/layers/network/__init__.py
vnet/layers/network/ip4.py
vnet/layers/network/ip4_header.py
vnet/layers/transport/__init__.py
vnet/layers/transport/tcp.py
vnet/layers/transport/tcp_header.py
vnet/layers/transport/udp.py
vnet/layers/transport/udp_header.py
vnet/lib/constants.py
vnet/lib/exceptions.py
vnet/lib/inet_cksum.py
vnet/lib/ip4_host.py
vnet/lib/layer.py
vnet/lib/proto_enum.py
vnet/lib/status_logger.py
vnet/lib/vpacket.py
vnet/net_addr/__init__.py
vnet/net_addr/ip4_address.py
vnet/net_addr/ip4_network.py
vnet/session/__init__.py
vnet/session/congestion_control.py
vnet/session/flow_control.py
vnet/session/tcp_session.py
vnet/session/vsession.py
vnet/structs_mapper/common.py
vnet/structs_mapper/gbn.py
vnet/structs_mapper/rdup_struct.py
vnet/topology/__init__.py
vnet/topology/conns_service.py
vnet/topology/netgrp_service.py
vnet/topology/vnet.py
vnet_kernel-0.6.0.dist-info/METADATA
vnet_kernel-0.6.0.dist-info/WHEEL
vnet_kernel-0.6.0.dist-info/top_level.txt
vnet_kernel-0.6.0.dist-info/RECORD
