Metadata-Version: 2.4
Name: vnet-kernel
Version: 0.6.0
Summary: virtual network project
Requires-Python: >=3.11
Requires-Dist: posix-ipc>=1.1.1
Requires-Dist: scapy==2.6.1
Provides-Extra: dev
Requires-Dist: pytest>=8.3.3; extra == "dev"
Requires-Dist: ruff==0.7.2; extra == "dev"
Requires-Dist: pytest-cov; extra == "dev"
Provides-Extra: doc
Requires-Dist: mkdocs-material; extra == "doc"
Requires-Dist: mkdocs-mermaid2-plugin; extra == "doc"
